miniappi/__init__.py
miniappi/__main__.py
miniappi/config.py
miniappi/content/__init__.py
miniappi/content/loading.py
miniappi/content/v0/__init__.py
miniappi/content/v0/cards/__init__.py
miniappi/content/v0/cards/card.py
miniappi/content/v0/code_block.py
miniappi/content/v0/forms/__init__.py
miniappi/content/v0/forms/dynamic_form.py
miniappi/content/v0/layouts/__init__.py
miniappi/content/v0/layouts/column.py
miniappi/content/v0/layouts/grid.py
miniappi/content/v0/layouts/row.py
miniappi/content/v0/title.py
miniappi/content/v0/widgets/__init__.py
miniappi/content/v0/widgets/button.py
miniappi/content/v0/widgets/drop_down.py
miniappi/content/v0/widgets/editor.py
miniappi/content/v0/widgets/input_number.py
miniappi/content/v0/widgets/input_text.py
miniappi/content/v0/widgets/knob.py
miniappi/core/__init__.py
miniappi/core/app.py
miniappi/core/connection/__init__.py
miniappi/core/connection/base.py
miniappi/core/connection/mock.py
miniappi/core/connection/websocket.py
miniappi/core/context.py
miniappi/core/exceptions.py
miniappi/core/logging.py
miniappi/core/models/__init__.py
miniappi/core/models/callbacks.py
miniappi/core/models/content.py
miniappi/core/models/context.py
miniappi/core/models/message_types.py
miniappi/core/models/references.py
miniappi/core/session.py
miniappi/core/utils/__init__.py
miniappi/core/utils/message.py
miniappi/flow/__init__.py
miniappi/flow/app.py
miniappi/flow/interact.py
miniappi/flow/scope.py
miniappi/ref/__init__.py
miniappi/ref/feed.py
miniappi/testing/__init__.py
miniappi/testing/external.py
miniappi-0.1.8.dist-info/licenses/LICENSE
miniappi-0.1.8.dist-info/WHEEL
miniappi-0.1.8.dist-info/entry_points.txt
miniappi-0.1.8.dist-info/METADATA
miniappi-0.1.8.dist-info/RECORD
