Metadata-Version: 2.4
Name: miniappi
Version: 0.1.8
Summary: Miniappi app launcher library
Author: Mikael Koli
Author-email: Mikael Koli <mikael.koli@miniappi.com>
License-File: LICENSE
Classifier: Development Status :: 3 - Alpha
Classifier: Intended Audience :: Developers
Classifier: Programming Language :: Python :: 3.13
Requires-Dist: httpx-ws>=0.8.0
Requires-Dist: pydantic>=2.11.7
Requires-Dist: pydantic-settings>=2.10.1
Requires-Dist: rich>=14.2.0
Requires-Python: >=3.13
Project-URL: Documentation, https://python-docs.miniappi.com/
Project-URL: Homepage, https://miniappi.com/
Project-URL: Repository, https://github.com/Miksus/miniappi-python.git
